[
  {
    "tag": "ruin2021",
    "albumName": "Ruin",
    "bandcamp": "https://cultofoccult.bandcamp.com/album/ruin",
    "imageUrl": "https://f4.bcbits.com/img/a2039861910_10.jpg",
    "songs": ["Ruin", "nuiRe"]
  },
  {
    "tag": "antilife2018",
    "albumName": "Anti Life",
    "bandcamp": "https://cultofoccult.bandcamp.com/album/anti-life-2",
    "imageUrl": "https://f4.bcbits.com/img/a0210801689_10.jpg",
    "songs": ["AL", "NI", "TF", "IE"]
  },
  {
    "tag": "splitwithgrimvandoom2017",
    "albumName": "Split With Grim Van Doom",
    "bandcamp": "https://cultofoccult.bandcamp.com/album/split-with-grim-van-doom",
    "imageUrl": "https://f4.bcbits.com/img/a0898232008_10.jpg",
    "songs": [
      "Cult of Occult - Black Sea",
      "Grim van Doom - Crimson",
      "Grim van Doom - Interlude",
      "Grim van Doom - Rust",
      "Grim van Doom - Azure"
    ]
  },
  {
    "tag": "fivedegreesofinsanity2015",
    "albumName": "Five Degrees Of Insanity",
    "bandcamp": "https://cultofoccult.bandcamp.com/album/five-degrees-of-insanity",
    "imageUrl": "https://f4.bcbits.com/img/a3814932014_10.jpg",
    "songs": ["Alcoholic", "Nihilistic", "Misanthropic", "Psychotic", "Satanic"]
  },
  {
    "tag": "hicestdomusdiaboli2013",
    "albumName": "HIC EST DOMUS DIABOLI",
    "bandcamp": "https://cultofoccult.bandcamp.com/album/hic-est-domus-diaboli",
    "imageUrl": "https://f4.bcbits.com/img/a3387200280_16.jpg",
    "songs": [
      "IN VINO VERITAS",
      "PRO DIABOLUS MORI",
      "OPUS AD ODIO",
      "DCLXVI",
      "REQUIEM",
      "MAGNA ERIPE"
    ]
  },
  {
    "tag": "cultofoccult2011",
    "albumName": "CULT OF OCCULT",
    "bandcamp": "https://cultofoccult.bandcamp.com/album/cult-of-occult",
    "imageUrl": "https://f4.bcbits.com/img/a4265651265_16.jpg",
    "songs": [
      "Blurry And Muzzy",
      "I Hate You",
      "Walking In The Desert",
      "Perfect Love",
      "Cult Of Occult"
    ]
  },
  {
    "tag": "rmxfrmhll2015",
    "albumName": "RMXFRMHLL",
    "bandcamp": "https://cultofoccult.bandcamp.com/album/rmxfrmhll",
    "imageUrl": "https://f4.bcbits.com/img/a2032268789_16.jpg",
    "songs": ["RMXFRMHLL"]
  },
  {
    "tag": "thisplanunsanecover2017",
    "albumName": "THIS PLAN (Unsane cover)",
    "bandcamp": "https://cultofoccult.bandcamp.com/album/this-plan-unsane-cover",
    "imageUrl": "https://f4.bcbits.com/img/a3345460996_16.jpg",
    "songs": ["THIS PLAN"]
  },
  {
    "tag": "insidethesunncover2015",
    "albumName": "INSIDE THE SUNN​)​)​) (Sleep cover)",
    "bandcamp": "https://cultofoccult.bandcamp.com/album/inside-the-sunn-sleep-cover",
    "imageUrl": "https://f4.bcbits.com/img/a2880537314_16.jpg",
    "songs": ["INSIDE THE SUNN​)​)​)"]
  },
  {
    "tag": "childrenofthegravecover2014",
    "albumName": "CHILDREN OF THE GRAVE (Black Sabbath cover)",
    "bandcamp": "https://cultofoccult.bandcamp.com/album/children-of-the-grave-black-sabbath-cover",
    "imageUrl": "https://f4.bcbits.com/img/a0637385541_16.jpg",
    "songs": ["Children of the Grave"]
  }
]
